setup.py
src/impaf_jinja2.egg-info/PKG-INFO
src/impaf_jinja2.egg-info/SOURCES.txt
src/impaf_jinja2.egg-info/dependency_links.txt
src/impaf_jinja2.egg-info/namespace_packages.txt
src/impaf_jinja2.egg-info/not-zip-safe
src/impaf_jinja2.egg-info/requires.txt
src/impaf_jinja2.egg-info/top_level.txt
src/implugin/__init__.py
src/implugin/jinja2/__init__.py
src/implugin/jinja2/application.py
src/implugin/jinja2/requestable.py
src/implugin/jinja2/widget.py
src/implugin/jinja2/tests/__init__.py
src/implugin/jinja2/tests/test_application.py
src/implugin/jinja2/tests/test_requestable.py
src/implugin/jinja2/tests/test_widget.py