Metadata-Version: 1.0
Name: impaf-jinja2
Version: 0.1
Summary: Jinja2 plugin for Impaf.
Home-page: UNKNOWN
Author: UNKNOWN
Author-email: UNKNOWN
License: Apache License 2.0
Platform: UNKNOWN
